LICENSE
README.md
setup.py
nonebot_plugin_brainfuck/__init__.py
nonebot_plugin_brainfuck/brainfuck_interpreter.py
nonebot_plugin_brainfuck/error_info.py
nonebot_plugin_brainfuck.egg-info/PKG-INFO
nonebot_plugin_brainfuck.egg-info/SOURCES.txt
nonebot_plugin_brainfuck.egg-info/dependency_links.txt
nonebot_plugin_brainfuck.egg-info/requires.txt
nonebot_plugin_brainfuck.egg-info/top_level.txt
nonebot_plugin_brainfuck.egg-info/zip-safe