Metadata-Version: 2.1
Name: nonebot-plugin-brainfuck
Version: 1.0.4
Summary: a brainfuck interpreter for nonebot
Home-page: https://github.com/campanulamediuml/nonebot-plugin-brainfuck
Author: campanula
Author-email: campanulamediuml@gmail.com
License: MIT
Keywords: brainfuck
Platform: any
Classifier: License :: OSI Approved :: MIT License
Classifier: Intended Audience :: Developers
Classifier: Operating System :: OS Independent
Classifier: Programming Language :: Python :: 3
Requires-Python: >=3.6
License-File: LICENSE
